{
  "lastBuildDate": "Thu, 12 Jul 2018 14:06:51 +0900",
  "total": 4409093,
  "start": 401,
  "display": 100,
  "items": [
    {
      "title": "<b>경기도</b> 공무원, 명찰 달기 싫다면 공무원증을 가슴에 달라",
      "originallink": "http://www.ohmynews.com/NWS_Web/View/at_pg.aspx?CNTN_CD=A0002452941&CMPT_CD=P0010&utm_source=naver&utm_medium=newsearch&utm_campaign=naver_news",
      "link": "http://news.naver.com/main/read.nhn?mode=LSD&mid=sec&sid1=102&oid=047&aid=0002195865",
      "description": "지난 5일 <b>경기도</b>가 자치행정국 총무과가 내부행정망 공람을 통해 전 직원이 근무시간에 명찰을 패용할 수 있도록 조치했다. 이에 <b>경기도</b>공무원노동조합은 '공무원증이 있는데 명찰 패용을 지시한 것은 예산을 낭비라면서... ",
      "pubDate": "Tue, 10 Jul 2018 14:18:00 +0900"
    },
    {
      "title": "<b>경기도</b>, 아파트 거주 위기가구 2,612세대 긴급지원",
      "originallink": "http://www.newstown.co.kr/news/articleView.html?idxno=332136",
      "link": "http://www.newstown.co.kr/news/articleView.html?idxno=332136",
      "description": "<b>경기도</b>가 아파트에 거주하는 복지사각지대 위기가구 2,612세대를 발굴해 긴급 지원했다. 도는 충북 증평군... 라호익 <b>경기도</b> 복지정책과장은 &quot;이번 조사에서 발굴된 위기가구에 대해서는 지속적인 모니터링을 통해... ",
      "pubDate": "Wed, 11 Jul 2018 02:16:00 +0900"
    },
    {
      "title": "이재명 <b>경기도</b>지사, 제10대 <b>경기도</b>의회 개원식 축사",
      "originallink": "http://www.ilyoseoul.co.kr/news/articleView.html?idxno=242028",
      "link": "http://www.ilyoseoul.co.kr/news/articleView.html?idxno=242028",
      "description": "[일요서울｜수원 강의석 기자]  이재명 <b>경기도</b>지사가 <b>경기도</b>의회에 협치를 강조하며 새로운 정치의 모범을 만들자고 손을 내밀었다.   이재명 도지사는 10일 제10대 <b>경기도</b>의회 개원식 축사를 통해 &quot;지난... ",
      "pubDate": "Tue, 10 Jul 2018 17:30:00 +0900"
    },
    {
      "title": "이화영 <b>경기도</b> 연정부지사 10일 공식 취임",
      "originallink": "http://www.ohmynews.com/NWS_Web/View/at_pg.aspx?CNTN_CD=A0002452998&CMPT_CD=P0010&utm_source=naver&utm_medium=newsearch&utm_campaign=naver_news",
      "link": "http://news.naver.com/main/read.nhn?mode=LSD&mid=sec&sid1=100&oid=047&aid=0002195882",
      "description": "이화영 부지사 “경기 북부를 한반도 신경제지도 중심지로 만들겠다” [ ▲  이화영 연정부지사 임명장 수여 ⓒ <b>경기도</b> 이화영 <b>경기도</b> 연정부지사가 10일 오전 이재명 <b>경기도</b>지사로부터 임명장을 받고 공식 취임했다. 이... ",
      "pubDate": "Tue, 10 Jul 2018 14:56:00 +0900"
    },
    {
      "title": "<b>경기도</b>의회, 개원식 갖고 희망의 닷 올렸다",
      "originallink": "http://www.asiatime.co.kr/news/articleView.html?idxno=187685",
      "link": "http://www.asiatime.co.kr/news/articleView.html?idxno=187685",
      "description": "/사진제공=<b>경기도</b>의회 /사진제공=<b>경기도</b>의회 [아시아타임즈=권혁철 기자]<b>경기도</b>의회는 10일 개원식을 개최하고 임기 4년의 의정활동을 본격 시작했다. 이날 개원식에 앞서 오전 본회의장에서 진행된 의장단... ",
      "pubDate": "Tue, 10 Jul 2018 17:35:00 +0900"
    },
    {
      "title": "제10대 <b>경기도</b>의회 개원축하연, 도지사·의장 담화 중",
      "originallink": "http://www.nspna.com/news/?mode=view&newsid=293286",
      "link": "http://www.nspna.com/news/?mode=view&newsid=293286",
      "description": "(경기=NSP통신) 민경호 기자 = 제10대 <b>경기도</b>의회 개원축하연이 10일 오후 2시 30분 <b>경기도</b>의회 1층 로비에서 열린 가운데 이재명 <b>경기도</b>지사와 송한준 <b>경기도</b>의회 의장이 귓속말을 하고 있다. NSP통신/NSP... ",
      "pubDate": "Tue, 10 Jul 2018 20:24:00 +0900"
    },
    {
      "title": "선서하는 제10대 <b>경기도</b>의회 의원들",
      "originallink": "http://news1.kr/photos/view/?3200023",
      "link": "http://news.naver.com/main/read.nhn?mode=LSD&mid=sec&sid1=102&oid=421&aid=0003474362",
      "description": "10일 오후 <b>경기도</b> 수원시 <b>경기도</b>의회 본회의장에서 열린 제10대 <b>경기도</b>의회 개원식에 참석한 의원들이 선서를 하고 있다. 2018.7.10/뉴스1 5zzang@news1.kr ▶ [뉴스1] 채널설정하기 ▶ 제보하기 ▶ 2018 러시아... ",
      "pubDate": "Tue, 10 Jul 2018 15:07:00 +0900"
    },
    {
      "title": "'2018 제1회 <b>경기도</b> 도로안전 포럼' 11일 개최",
      "originallink": "http://www.newsis.com/view/?id=NISX20180710_0000359013&cID=10817&pID=10800",
      "link": "http://news.naver.com/main/read.nhn?mode=LSD&mid=sec&sid1=102&oid=003&aid=0008696621",
      "description": "=<b>경기도</b> 도로업무 담당자들이 실제 도로사업 현장에서 더 나은 도로시공 및 안전사고 예방 기법을 추진하기 위해 머리를 맞댄다. <b>경기도</b>는 오는 11일 오후 2시부터 '세종~구리 고속도로 사업' 현장서 도 및 시·군... ",
      "pubDate": "Tue, 10 Jul 2018 07:33:00 +0900"
    },
    {
      "title": "<b>경기도</b>내 문화재 건축물, 10월부터 재난 대응 지침 마련된다",
      "originallink": "http://www.joongboo.com/?mod=news&act=articleView&idxno=1266688",
      "link": "http://www.joongboo.com/?mod=news&act=articleView&idxno=1266688",
      "description": "<b>경기도</b>가 화재, 지진 등 재난 발생시 문화재 시설을 보호, 보존하기 위한 대응 지침서 마련을 이르면 오는... 10일 <b>경기도</b>에 따르면 도는 ‘<b>경기도</b> 문화재 보호 조례 시행규칙 일부개정규칙안’을 입법예고, 이달 말까지... ",
      "pubDate": "Tue, 10 Jul 2018 22:50:00 +0900"
    },
    {
      "title": "<b>경기도</b> 통상촉진단, UAE서 724만 달러 수출활로 '낭보'",
      "originallink": "http://www.suwon.com/news/articleView.html?idxno=125703",
      "link": "http://www.suwon.com/news/articleView.html?idxno=125703",
      "description": "UAE 에프티에스 &lt;사진= <b>경기도</b>&gt; <b>경기도</b>의 지원을 받은 수출 유망 중소기업 10개사가 아랍에미리트(UAE) 시장에서 수출활로 낭보를 전해왔다. 10일 <b>경기도</b>에 따르면, 중동시장 개척을 위해 <b>경기도</b> 주최, (재)... ",
      "pubDate": "Tue, 10 Jul 2018 08:00:00 +0900"
    },
    {
      "title": "‘<b>경기도</b> 협치 파트너’ 10대 <b>경기도</b>의회 공식 개원…새로운 경기 기대감 UP",
      "originallink": "http://www.kyeonggi.com/?mod=news&act=articleView&idxno=1495712",
      "link": "http://www.kyeonggi.com/?mod=news&act=articleView&idxno=1495712",
      "description": "▲ 제10대 <b>경기도</b>의회가 10일 개원식을 갖고 본격적인 활동에 들어갔다. 이날 도의회 본회의장에서 열린... 김시범기자 민선 7기 <b>경기도</b>의 협치 파트너가 될 제10대 <b>경기도</b>의회가 10일 공식 개원했다. 전국 최대 광역의회인... ",
      "pubDate": "Tue, 10 Jul 2018 21:52:00 +0900"
    },
    {
      "title": "<b>경기도</b>, 양성평등 문화 확산 위한 '젠더스쿨' 운영",
      "originallink": "http://www.newstown.co.kr/news/articleView.html?idxno=332274",
      "link": "http://www.newstown.co.kr/news/articleView.html?idxno=332274",
      "description": "<b>경기도</b>가 양성평등 문화 확산을 위해 올해부터 성인지 교육인 '젠더스쿨'을 운영한다. 대상은 주민자치위원... 앞으로 <b>경기도</b>는 젠더스쿨 운영의 실효성을 높이기 위해 다양한 교육대상자를 발굴하고 대상자 눈높이에... ",
      "pubDate": "Wed, 11 Jul 2018 20:38:00 +0900"
    },
    {
      "title": "제10대 <b>경기도</b>의회 개원...송한준 의장 선출",
      "originallink": "http://www.newsway.co.kr/news/view?tp=1&ud=2018071017024265620",
      "link": "http://www.newsway.co.kr/news/view?tp=1&ud=2018071017024265620",
      "description": "10일 열린 제10대 <b>경기도</b>의회 개원식에서 송한준 의장의 선창으로 전체 의원이 선서문을 낭독하고 있다. 제10대 <b>경기도</b>의회가 10일 개원식을 열고 임기 4년의 의정활동에 돌입했다. 개원식에 앞서 이날 오전... ",
      "pubDate": "Tue, 10 Jul 2018 17:04:00 +0900"
    },
    {
      "title": "<b>경기도</b>, 현장중심 계약심사 올 상반기 661억 원 조정",
      "originallink": "http://www.hkbs.co.kr/news/articleView.html?idxno=475453",
      "link": "http://www.hkbs.co.kr/news/articleView.html?idxno=475453",
      "description": "[경기=환경일보]  정재형 기자 = <b>경기도</b>가 올해 상반기 계약심사를 통해 661억 원의 사업비를... 최인수 <b>경기도</b> 감사관은 “계약심사의 목적은 발주부서에서 기준과 달리 과다 산정 또는 과소하게... ",
      "pubDate": "Wed, 11 Jul 2018 12:48:00 +0900"
    },
    {
      "title": "<b>경기도</b>, 상반기 계약심사 통해 661억원 사업비 조정",
      "originallink": "http://www.enewstoday.co.kr/news/articleView.html?idxno=1210452",
      "link": "http://www.enewstoday.co.kr/news/articleView.html?idxno=1210452",
      "description": "<b>경기도</b>청 전경 [이뉴스투데이 경인취재본부 김승희 기자] <b>경기도</b>가 올해 상반기 계약심사를 통해 661억원의 사업비를 조정했다고 11일 밝혔다. 이는 지난해 상반기 조정액 540억원 대비 121억원 늘어난 규모다.... ",
      "pubDate": "Wed, 11 Jul 2018 08:04:00 +0900"
    },
    {
      "title": "<b>경기도</b> 인수위, 고질·고액 체납 뿌리뽑는다",
      "originallink": "http://news1.kr/articles/?3367981",
      "link": "http://news.naver.com/main/read.nhn?mode=LSD&mid=sec&sid1=102&oid=421&aid=0003474112",
      "description": "이재명 <b>경기도</b>지사 당선인이 28일 오전 차세대융합기술원 16층에서 열린 민선7기 도지사직 인수위원회인 새로운 경기위원회 4차 회의를 주재하고 있다. (<b>경기도</b> 제공) © News1 진현권 기자  민선 7기 <b>경기도</b>지사직... ",
      "pubDate": "Tue, 10 Jul 2018 14:02:00 +0900"
    },
    {
      "title": "<b>경기도</b>, 올 상반기 계약심사 1천388건 실시",
      "originallink": "http://www.dtoday.co.kr/news/articleView.html?idxno=271633",
      "link": "http://www.dtoday.co.kr/news/articleView.html?idxno=271633",
      "description": "[일간투데이 한영민 기자] <b>경기도</b>가 올해 상반기 계약심사를 통해 661억 원의 사업비를 조정했다. 이는... 한편, <b>경기도</b>는 2008년부터 2018년 상반기까지 10년 동안 2만 306건을 대상으로 계약심사를 실시해 1조 6천152억... ",
      "pubDate": "Wed, 11 Jul 2018 15:19:00 +0900"
    },
    {
      "title": "<b>경기도</b>교육청, 학교폭력 관련 법률 지원 연수",
      "originallink": "http://www.enewstoday.co.kr/news/articleView.html?idxno=1210533",
      "link": "http://www.enewstoday.co.kr/news/articleView.html?idxno=1210533",
      "description": "[이뉴스투데이 경인취재본부 김승희 기자] <b>경기도</b>교육청은 오는 12일부터 17일까지 3차에 걸쳐 북부청사 및 <b>경기도</b>교육복지센터에서‘2018년 학교폭력 관련 법률 지원 연수’를 실시한다고 밝혔다. 이번 연수는 학교폭력... ",
      "pubDate": "Wed, 11 Jul 2018 10:26:00 +0900"
    },
    {
      "title": "이화영 <b>경기도</b> 연정부지사 취임…&quot;이재명 지사와 新경기북부 일구겠다&quot;",
      "originallink": "http://www.nocutnews.co.kr/news/4998280",
      "link": "http://news.naver.com/main/read.nhn?mode=LSD&mid=sec&sid1=102&oid=079&aid=0003121757",
      "description": "이재명 <b>경기도</b>지사(사진 왼쪽)로부터 임몀장을 받은 후 함께 기념촬영을 하고 있다. (사진=<b>경기도</b>청 제공) 이화영 <b>경기도</b> 연정부지사 내정자가 10일 취임했다. 이재명 지사와 마찬가지로 취임식은 생략됐다. 이 부지사는... ",
      "pubDate": "Tue, 10 Jul 2018 14:00:00 +0900"
    },
    {
      "title": "[금휘궁(점집) 김금휘의 무속이야기] <b>경기도</b> 구리시에서 전승되고 있는 ‘구리...",
      "originallink": "http://www.g-enews.com/ko-kr/news/article/news_all/201807101400305174e8b8a793f7_3/article.html",
      "link": "http://www.g-enews.com/ko-kr/news/article/news_all/201807101400305174e8b8a793f7_3/article.html",
      "description": "● <b>경기도</b> 구리시에서 전승되고 있는 ‘구리갈매동도당굿’ ‘구리갈매동 도당굿’은 <b>경기도</b> 구리시 갈매동에서 전승되고 있는 마을제의다. 현지에서는 ‘갈매동 산치성 도당굿’이라고 한다. 이 굿은 1995년 8월 7일에... ",
      "pubDate": "Tue, 10 Jul 2018 14:02:00 +0900"
    },
    {
      "title": "안양소방서, <b>경기도</b>의원 초청 간담회 개최",
      "originallink": "http://www.joongboo.com/?mod=news&act=articleView&idxno=1266741",
      "link": "http://www.joongboo.com/?mod=news&act=articleView&idxno=1266741",
      "description": "▲ 안양소방서가 민선 10기 <b>경기도</b>의회 의원들을 초청, 간담회를 가졌다. 사진=안양소방서 안양소방서는 지난 9일 안전도시 안양시 구축을 위한 <b>경기도</b>의원 초청 소방안전정책간담회를 개최했다. 이번 간담회는 민선... ",
      "pubDate": "Tue, 10 Jul 2018 22:52:00 +0900"
    },
    {
      "title": "[<b>경기도</b>] 올 상반기 계약심사 1388건, 661억원 조정..예산 낭비 막아",
      "originallink": "http://www.ajunews.com/view/20180711085416716",
      "link": "http://www.ajunews.com/view/20180711085416716",
      "description": "2008년부터 올 상반기 10년 동안 2만306건 대상 1조6152억 조정 (수원)김문기 기자 kmg1007@ajunews.com <b>경기도</b>청 <b>경기도</b>가 올 상반기 계약심사를 통해 661억원의 사업비를 조정했다고 11일 밝혔다. 이는 지난해 상반기... ",
      "pubDate": "Wed, 11 Jul 2018 15:00:00 +0900"
    },
    {
      "title": "송한준, <b>경기도</b>의회 의장 선출돼",
      "originallink": "http://www.nspna.com/news/?mode=view&newsid=293259",
      "link": "http://www.nspna.com/news/?mode=view&newsid=293259",
      "description": "(경기=NSP통신) 민경호 기자 = 제10대 <b>경기도</b>의회가 10일 오전 10시 제1차 본회의, 제329회 임시회를 열고 4년간의 대장정을 시작했다. 이날 <b>경기도</b>의회는 본회의에서 의장·부의장 선거를 시작으로 첫 개의를... ",
      "pubDate": "Tue, 10 Jul 2018 17:30:00 +0900"
    },
    {
      "title": "<b>경기도</b>, 양성평등 문화 확산 위한 ‘젠더스쿨’ 운영",
      "originallink": "http://www.asiatoday.co.kr/view.php?key=20180711010006454",
      "link": "http://www.asiatoday.co.kr/view.php?key=20180711010006454",
      "description": "기자 = <b>경기도</b>가 양성평등 문화 확산을 위해 올해부터 성인지 교육인 ‘젠더스쿨’을 운영한다고 11일... <b>경기도</b>는 젠더스쿨 운영의 실효성을 높이기 위해 다양한 교육대상자를 발굴하고 대상자 눈높이에 맞춘 분야별... ",
      "pubDate": "Wed, 11 Jul 2018 10:40:00 +0900"
    },
    {
      "title": "<b>경기도</b>교육청 시민감사팀-유치원, 감사 놓고 첨예 대립",
      "originallink": "http://news1.kr/articles/?3367836",
      "link": "http://news.naver.com/main/read.nhn?mode=LSD&mid=sec&sid1=102&oid=421&aid=0003473712",
      "description": "<b>경기도</b>교육청 뉴스1(DB)© News1  <b>경기도</b>교육청 시민감사팀과 사립유치원이 특정감사를 놓고 첨예한 대립각을 세우고 있다. 감사팀은 자신들이 요구한 수감자료를 제출하지 않을 시 감사 없이 사법기관에... ",
      "pubDate": "Tue, 10 Jul 2018 11:44:00 +0900"
    },
    {
      "title": "&quot;<b>경기도</b>의회-집행부, <b>경기도</b>민 민생문제 해결에 협력하자&quot;",
      "originallink": "http://www.joongboo.com/?mod=news&act=articleView&idxno=1266777",
      "link": "http://www.joongboo.com/?mod=news&act=articleView&idxno=1266777",
      "description": "▲ 10일 오후 수원시 팔달구 <b>경기도</b>의회 1층 로비에 마련된 개원축하연 자리에서 송한준 <b>경기도</b>의회 의장(가운데), 이재명 <b>경기도</b>지사(가운데 왼쪽), 이재정 <b>경기도</b>교육감(가운데 오른쪽)등 참석자들이 손을 맞잡고... ",
      "pubDate": "Tue, 10 Jul 2018 22:53:00 +0900"
    },
    {
      "title": "<b>경기도</b>의회, '공약관리TF팀' 신설",
      "originallink": "http://www.newsworks.co.kr/news/articleView.html?idxno=199904",
      "link": "http://www.newsworks.co.kr/news/articleView.html?idxno=199904",
      "description": "송한준 <b>경기도</b>의회 의장. &lt;사진=<b>경기도</b>의회&gt; [뉴스웍스=한재갑 기자] <b>경기도</b>의회가 도의원들의 공약 실현을 위해 '공약관리TF'를 구성한다. 11일 도의회에 따르면, 공약관리TF는 5급 사무관을 팀장으로 일반직 공무원과... ",
      "pubDate": "Wed, 11 Jul 2018 17:57:00 +0900"
    },
    {
      "title": "['식약처 판매중단약' 파문]대형병원(<b>경기도</b>내 3곳)도 '발암물질 고혈압약' 처...",
      "originallink": "http://www.kyeongin.com/main/view.php?key=20180710010003600",
      "link": "http://www.kyeongin.com/main/view.php?key=20180710010003600",
      "description": "<b>경기도</b>내 대형병원 중 분당서울대병원과 <b>경기도</b>의료원 수원병원이 발암물질이 함유된 중국산 발사르탄 원료 혈압약을 처방한 것으로 확인된 가운데, 10일 오후 수원 성빈센트병원에 '문제가 된 약품을... ",
      "pubDate": "Tue, 10 Jul 2018 22:32:00 +0900"
    },
    {
      "title": "<b>경기도</b>, 경찰과 민생현안 해결 '파트너십'",
      "originallink": "http://www.kyeongin.com/main/view.php?key=20180710010003623",
      "link": "http://www.kyeongin.com/main/view.php?key=20180710010003623",
      "description": "10일 도지사직 인수위원회 안전행정분과위에 따르면 새로운 체제의 <b>경기도</b>에서 특사경은 기존 식품 위생... 이는 이재명 도지사의 공약인데, 그는 후보시절인 지난 5월 '삶이 안전한 <b>경기도</b>'를 만들겠다며 이러한 점들을... ",
      "pubDate": "Tue, 10 Jul 2018 22:32:00 +0900"
    },
    {
      "title": "제10대 <b>경기도</b>의회 개원…송한준 의장 선출 &quot;의회다운 의회 만들 터&quot;",
      "originallink": "http://kpenews.com/Board.aspx?BoardNo=16054",
      "link": "http://kpenews.com/Board.aspx?BoardNo=16054",
      "description": "제10대 <b>경기도</b>의회가 10일 개원했다. (사진=<b>경기도</b>의회) 송한준 <b>경기도</b>의회 신임 의장은 &quot;의회다운 의회&quot;를 기치로 전반기 의정 활동을 시작했다. (사진=<b>경기도</b>의회) [한국정경신문=이근항 기자] 제10대 <b>경기도</b>의회가 10일... ",
      "pubDate": "Tue, 10 Jul 2018 14:49:00 +0900"
    },
    {
      "title": "제10대 <b>경기도</b>의회 개원식 열고 본격 가동",
      "originallink": "http://www.enewstoday.co.kr/news/articleView.html?idxno=1210359",
      "link": "http://www.enewstoday.co.kr/news/articleView.html?idxno=1210359",
      "description": "10일 제10대 <b>경기도</b>의회가 개원식을 열고 본격적인 의정활동에 돌입했다. [이뉴스투데이 경인취재본부 김승희 기자] 6.13 지방선거를 통해 142명으로 구성된 제10대 <b>경기도</b>의회가 10일 개원식을 열고 본격적인... ",
      "pubDate": "Tue, 10 Jul 2018 17:46:00 +0900"
    },
    {
      "title": "이화영 <b>경기도</b> 연정부지사 취임…&quot;북부를 한반도 중심지로…&quot;",
      "originallink": "http://view.asiae.co.kr/news/view.htm?idxno=2018071014242549817",
      "link": "http://news.naver.com/main/read.nhn?mode=LSD&mid=sec&sid1=102&oid=277&aid=0004274396",
      "description": "[아시아경제(수원)=이영규 기자] 이화영 <b>경기도</b> 연정부지사가 10일 공식 취임했다. 이화영 연정부지사는 이날... 이 부지사는 이날 별도의 취임식을 생략한 채 곧바로 의정부 <b>경기도</b>청 북부청사 상황실로 이동해 경기북부... ",
      "pubDate": "Tue, 10 Jul 2018 14:24:00 +0900"
    },
    {
      "title": "이화영 <b>경기도</b> 연정부지사 취임, &quot;경기북부 신경제지도 중심지로 만들것&quot;",
      "originallink": "http://kpenews.com/Board.aspx?BoardNo=16040",
      "link": "http://kpenews.com/Board.aspx?BoardNo=16040",
      "description": "이재명 경기지사로 부터 임명장을 받은 이화영 민선7기 <b>경기도</b>연정부지사(사진=<b>경기도</b>청) [한국정경신문=이근항 기자] 이화영(사진 오른쪽) <b>경기도</b> 연정부지사가 10일 오전 이재명 <b>경기도</b>지사로부터 임명장을 받고 공식... ",
      "pubDate": "Tue, 10 Jul 2018 11:25:00 +0900"
    },
    {
      "title": "송한준 <b>경기도</b>의장 “도민에 꿈과 희망 드려야”",
      "originallink": "http://news1.kr/articles/?3368279",
      "link": "http://news.naver.com/main/read.nhn?mode=LSD&mid=sec&sid1=102&oid=421&aid=0003474774",
      "description": "10일 <b>경기도</b>의회 송한준(민주·안산1) 의원이 제10대 의회 전반기(2년) 의장으로 선출됐다. (사진제공=<b>경기도</b>의회)/2018.07.10© News1  제10대 <b>경기도</b>의회 전반기(2년)를 이끌 송한준(민주·안산1) 의장이 10일 개원사에서... ",
      "pubDate": "Tue, 10 Jul 2018 16:48:00 +0900"
    },
    {
      "title": "<b>경기도</b>재활공학서비스연구지원센터, '2018 보조공학 세미나' 개최",
      "originallink": "http://www.welfarenews.net/news/articleView.html?idxno=65478",
      "link": "http://www.welfarenews.net/news/articleView.html?idxno=65478",
      "description": "ⓒ<b>경기도</b>재활공학서비스연구지원센터 ⓒ<b>경기도</b>재활공학서비스연구지원센터 <b>경기도</b>재활공학서비스연구지원센터가 오는 13일 <b>경기도</b>장애인복지종합지원센터 누림에서 '2018 보조공학 세미나'를 연다. 이번 세미나는 최근... ",
      "pubDate": "Tue, 10 Jul 2018 10:20:00 +0900"
    },
    {
      "title": "<b>경기도</b>의회 안양상담소, “청소년 생활지도 사회 환경 변화 대책 논의”",
      "originallink": "http://www.breaknews.com/sub_read.html?uid=588881&section=sc2",
      "link": "http://www.breaknews.com/sub_read.html?uid=588881&section=sc2",
      "description": "<b>경기도</b>의회상담소에서 조광희 의원은 3일 ㈜삼경엠에스 엄연옥대표, 귀인중 조재수운영위원장과 청소년... 한편 <b>경기도</b>의회 지역상담소는 지역현안을 상담하여 도민 소통창구의 역할을 하고 있다. <b>경기도</b> 31개 시·군에... ",
      "pubDate": "Tue, 10 Jul 2018 10:16:00 +0900"
    },
    {
      "title": "이재명 <b>경기도</b>지사, 제10대 <b>경기도</b>의회 개원식 축사",
      "originallink": "http://www.newscj.com/news/articleView.html?idxno=536498",
      "link": "http://www.newscj.com/news/articleView.html?idxno=536498",
      "description": "&quot;경기 새로운 출발 기쁘고 영광스럽다 적극적인 협치로 정치의 모범 만들자 도민 행복위한 길이면 반대할 이유 없어&quot;  이재명 <b>경기도</b>지사가 10일 제10대 <b>경기도</b>의회 개원식에서 축사를 했다. 이날 축사를 통해 이 도지사는... ",
      "pubDate": "Tue, 10 Jul 2018 16:40:00 +0900"
    },
    {
      "title": "<b>경기도</b>의회, 제10대 개원식 희망찬 '출범'",
      "originallink": "http://www.newscj.com/news/articleView.html?idxno=536501",
      "link": "http://www.newscj.com/news/articleView.html?idxno=536501",
      "description": "6.13 지방선거를 통해 142명으로 구성된 제10대 <b>경기도</b>의회가 10일 개원식을 개최하고 임기 4년의 의정활동을... 제10대 <b>경기도</b>의회 전반기를 이끌게 됐다. 부의장에는 3선의 더불어민주당 김원기의원(의정부4)과... ",
      "pubDate": "Tue, 10 Jul 2018 16:48:00 +0900"
    },
    {
      "title": "<b>경기도</b> 통상촉진단, UAE서 724만 달러 수출활로 ‘낭보’",
      "originallink": "http://www.upkorea.net/news/articleView.html?idxno=348786",
      "link": "http://www.upkorea.net/news/articleView.html?idxno=348786",
      "description": "2018 <b>경기도</b> UAE 통상촉진단 [업코리아]<b>경기도</b>의 지원을 받은 수출 유망 중소기업 10개사가 아랍에미리트 시장에서 수출활로 낭보를 전해왔다. 10일 <b>경기도</b>에 따르면, 중동시장 개척을 위해 <b>경기도</b> 주최... ",
      "pubDate": "Tue, 10 Jul 2018 11:12:00 +0900"
    },
    {
      "title": "<b>경기도</b>, ‘새로운경기위원회’ 체납액 강력 징수 나서",
      "originallink": "http://www.betanews.net:8080/article/879375.html",
      "link": "http://www.betanews.net:8080/article/879375.html",
      "description": "<b>경기도</b>청/베타뉴스 [경기=베타뉴스]김성옥 기자=민선 7기 <b>경기도</b>지사직 인수위원회인 ‘새로운경기위원회’가 5천990억여 원(징수결정액 24조8,500억 중 2.4%)에 달하는 <b>경기도</b> 체납액에 대한 강력한 징수를 통해... ",
      "pubDate": "Tue, 10 Jul 2018 23:08:00 +0900"
    },
    {
      "title": "<b>경기도</b>, 20~31일 '경기 동네서점展' 참가 서점 모집",
      "originallink": "http://news1.kr/articles/?3367745",
      "link": "http://news.naver.com/main/read.nhn?mode=LSD&mid=sec&sid1=102&oid=421&aid=0003473398",
      "description": "<b>경기도</b>가 20일부터 31일까지 '2018 발견! 경기 동네서점展'에 참가할 지역서점을 모집한다. (<b>경기도</b> 제공) © News1 진현권 기자  <b>경기도</b>가 20일부터 31일까지 ‘2018 발견! 경기 동네서점展’에 참가할 지역서점을... ",
      "pubDate": "Tue, 10 Jul 2018 10:31:00 +0900"
    },
    {
      "title": "10대 <b>경기도</b>의회 10일 개원식",
      "originallink": "http://www.incheonilbo.com/?mod=news&act=articleView&idxno=817928",
      "link": "http://www.incheonilbo.com/?mod=news&act=articleView&idxno=817928",
      "description": "[인천일보] 제10대 <b>경기도</b>의회가 10일 개원식을 갖고 공식 출범한다. 9일 도의회에 따르면 제10대 <b>경기도</b>의회는 10일 제329회 임시회를 열고 전반기 도의회를 이끌어갈 의장과 2명의 부의장에 대한 선거를 진행한다.... ",
      "pubDate": "Tue, 10 Jul 2018 02:52:00 +0900"
    },
    {
      "title": "<b>경기도</b>, UAE 통상촉진단 724만 달러 수출 계약",
      "originallink": "http://www.ekn.kr/news/article.html?no=373213",
      "link": "http://www.ekn.kr/news/article.html?no=373213",
      "description": "<b>경기도</b>, UAE 통상촉진단 현지 바이어 상담 (사진=<b>경기도</b>) [수원=에너지경제신문 좌승훈 기자] <b>경기도</b>의 지원을 받은 수출 유망 중소기업 10개사가 아랍에미리트(UAE) 시장에서 724만 달러의 수출 계약을 맺었다. 10일... ",
      "pubDate": "Tue, 10 Jul 2018 11:44:00 +0900"
    },
    {
      "title": "<b>경기도</b>, '2018년도 제1회 도로안전포럼' 개최···시공·사고예방 기법 논의",
      "originallink": "http://www.ikld.kr/news/articleView.html?idxno=96465",
      "link": "http://www.ikld.kr/news/articleView.html?idxno=96465",
      "description": "[국토일보 김주영 기자]  <b>경기도</b>가 실제 도로사업 현장에서 더 나은 도로 시공 및 안전사고 예방 기법을 추진하기 위해 머리를 맞댄다. <b>경기도</b>는 오는 11일 '세종~구리 고속도로 건설사업' 현장에서... ",
      "pubDate": "Tue, 10 Jul 2018 10:42:00 +0900"
    },
    {
      "title": "도 평생교육진흥원 ‘<b>경기도</b> 평생학습 동아리 관계자 연수 및 컨설팅’ 진행",
      "originallink": "http://www.upkorea.net/news/articleView.html?idxno=348815",
      "link": "http://www.upkorea.net/news/articleView.html?idxno=348815",
      "description": "상세 일정 [업코리아]<b>경기도</b>와 <b>경기도</b>평생교육진흥원은 10일 의정부시 평생교육비전센터에서 도내 평생학습 동아리의 지속적인 성장 및 발전 방안 모색을 위한 ‘2018 <b>경기도</b> 평생학습 동아리 관계자 연수 및 컨설팅’을... ",
      "pubDate": "Tue, 10 Jul 2018 11:12:00 +0900"
    },
    {
      "title": "<b>경기도</b>지사직 인수위 “현 준공영제 중지...노선입찰제 중심 새경기 준공영제...",
      "originallink": "http://www.newsway.co.kr/news/view?tp=1&ud=2018071023264712091",
      "link": "http://www.newsway.co.kr/news/view?tp=1&ud=2018071023264712091",
      "description": "<b>경기도</b>지사직 인수위원회 교통대책특별위원회(위원장 김경협)는 10일 시외면허로 전환된 공항버스의 한정면허 원복(元復), 노선입찰제 중심의 ‘새경기 준공영제’ 도입, 경기교통공사 설립 등을 민선7기 <b>경기도</b>... ",
      "pubDate": "Tue, 10 Jul 2018 23:28:00 +0900"
    },
    {
      "title": "이재명 <b>경기도</b>지사, 제10회 <b>경기도</b>의회 개원식 축사",
      "originallink": "http://news1.kr/photos/view/?3200177",
      "link": "http://news.naver.com/main/read.nhn?mode=LSD&mid=sec&sid1=102&oid=421&aid=0003474525",
      "description": "이재명 <b>경기도</b>지사가 10일 오후 <b>경기도</b> 수원시 <b>경기도</b>의회 본회의장에서 열린 제10대 <b>경기도</b>의회 개원식에 참석해 축사를 하고 있다. 2018.7.10/뉴스1 5zzang@news1.kr ▶ [뉴스1] 채널설정하기 ▶ 제보하기... ",
      "pubDate": "Tue, 10 Jul 2018 15:37:00 +0900"
    },
    {
      "title": "<b>경기도</b>내 공항버스 시외버스 전환, 한 달만에 '한정면허'로 환원",
      "originallink": "http://news.hankyung.com/article/201807106191h",
      "link": "http://news.naver.com/main/read.nhn?mode=LSD&mid=sec&sid1=102&oid=015&aid=0003976705",
      "description": "지난달 한정면허 기간이 만료돼 시외버스로 전환됐던 <b>경기도</b>내 공항버스 23개 노선이 원래대로 한정면허로 환원된다. 또 광역버스 준공영제에 노선입찰제를 보완한 '새경기 준공영제'도 도입된다. 민선 7기 이재명 <b>경기도</b>... ",
      "pubDate": "Tue, 10 Jul 2018 14:57:00 +0900"
    },
    {
      "title": "<b>경기도</b> 광역버스 준공영제 '노선입찰제' 내년 시범운영할 듯",
      "originallink": "http://www.incheonilbo.com/?mod=news&act=articleView&idxno=817955",
      "link": "http://www.incheonilbo.com/?mod=news&act=articleView&idxno=817955",
      "description": "[인천일보] <b>경기도</b>가 버스 공공성 강화를 위해 '광역버스 준공영제'에 노선입찰제 방식을 도입하고... 이 지사도 6·13지방선거과정에서 &quot;현행 <b>경기도</b> 광역버스 준공영제가 버스회사에 막대한 보조금을 주면서도... ",
      "pubDate": "Tue, 10 Jul 2018 02:52:00 +0900"
    },
    {
      "title": "<b>경기도</b>, 도로 안전사고 예방 해법 현장에서 찾는다",
      "originallink": "http://www.asiatime.co.kr/news/articleView.html?idxno=187600",
      "link": "http://www.asiatime.co.kr/news/articleView.html?idxno=187600",
      "description": "[아시아타임즈=권혁철 기자] <b>경기도</b>가 도로 안전사고 예방 해법을 찾는다. 이를 위해 '<b>경기도</b> 도로안전 포럼'을 개최해 <b>경기도</b>와 시·군 도로업무 담당자 100여명들이 머리를 맞댄다. 도로사업 현장에서 토론하는 방식을... ",
      "pubDate": "Tue, 10 Jul 2018 13:51:00 +0900"
    },
    {
      "title": "<b>경기도</b> 아파트 거주 위기가구 2600세대 긴급지원",
      "originallink": "http://www.hankookilbo.com/v/f2dc0097387142c39fd321a9d97c9c5a",
      "link": "http://news.naver.com/main/read.nhn?mode=LSD&mid=sec&sid1=102&oid=469&aid=0000313164",
      "description": "“제2 증평 모녀 없도록 복지안전망 촘촘히 꾸릴 것” <b>경기도</b>청사 전경. <b>경기도</b> 제공 <b>경기도</b>가 아파트에 거주하는 복지사각지대 위기가구 2,612세대를 발굴해 긴급 지원했다고 10일 밝혔다. 도는 충북 증평군 모녀... ",
      "pubDate": "Tue, 10 Jul 2018 09:56:00 +0900"
    },
    {
      "title": "<b>경기도</b>, 수천억 체납액 강력 징수 나선다",
      "originallink": "http://www.newsis.com/view/?id=NISX20180710_0000359677&cID=10803&pID=14000",
      "link": "http://news.naver.com/main/read.nhn?mode=LSD&mid=sec&sid1=102&oid=003&aid=0008697839",
      "description": "【수원=뉴시스】 수도권취재팀 = 민선 7기 <b>경기도</b>지사직 인수위원회인 ‘새로운경기위원회’가 5990억원(징수결정액 24조8500억 중 2.4%)에 달하는 <b>경기도</b> 체납액에 대한 강력한 징수를 통해 조세 정의 실현에 나선다.... ",
      "pubDate": "Tue, 10 Jul 2018 14:57:00 +0900"
    },
    {
      "title": "선서하는 제10대 <b>경기도</b>의회 의원들",
      "originallink": "http://news1.kr/photos/view/?3200194",
      "link": "http://news.naver.com/main/read.nhn?mode=LSD&mid=sec&sid1=102&oid=421&aid=0003474549",
      "description": "10일 오후 <b>경기도</b> 수원시 <b>경기도</b>의회 본회의장에서 열린 제10대 <b>경기도</b>의회 개원식에 참석한 의원들이 선서를 하고 있다. 2018.7.10/뉴스1 5zzang@news1.kr ▶ [뉴스1] 채널설정하기 ▶ 제보하기 ▶ 2018 러시아... ",
      "pubDate": "Tue, 10 Jul 2018 15:44:00 +0900"
    },
    {
      "title": "<b>경기도</b>의회 개원, 초선 이재명, 재선 이재정, 삼선 송한준 '건배'",
      "originallink": "http://www.newscj.com/news/articleView.html?idxno=536485",
      "link": "http://www.newscj.com/news/articleView.html?idxno=536485",
      "description": "   제10대 <b>경기도</b>의회 개원 축하연이 10일 <b>경기도</b>의회  1층 로비에서 열린 가운데 이재명 <b>경기도</b>지사, 송한준 <b>경기도</b>의회 의장, 이재정 경기교육감이 사이좋게 건배하고 있다.",
      "pubDate": "Tue, 10 Jul 2018 16:00:00 +0900"
    },
    {
      "title": "<b>경기도</b>, 일반인 생활 원고 모집",
      "originallink": "http://www.gukjenews.com/news/articleView.html?idxno=955735",
      "link": "http://www.gukjenews.com/news/articleView.html?idxno=955735",
      "description": "(수원=국제뉴스) 김만구 기자 = <b>경기도</b>는 일반인에게 책을 펴낼 수 있는 기회를 제공하는 '경기 히든작가... 다음달 1~15일 <b>경기도</b>콘텐츠진흥원으로 우편 또는 온라인으로 제출하면 된다. 도는 심사를 통해 분야별 10편을... ",
      "pubDate": "Wed, 11 Jul 2018 09:04:00 +0900"
    },
    {
      "title": "<b>경기도</b>, 도로시공 안전 및 사고예방에 머리 맞댄다",
      "originallink": "http://www.cnews.co.kr/uhtml/read.jsp?idxno=201807101009056920876",
      "link": "http://www.cnews.co.kr/uhtml/read.jsp?idxno=201807101009056920876",
      "description": "<b>경기도</b> 도로업무 담당자들이 실제 도로사업 현장에서 더 나은 도로시공 및 안전사고 예방 기법을 추진하기 위해 머리를 맞댄다. <b>경기도</b>는 오는 11일 ‘세종~구리 고속도로 사업’ 현장서 도 및 시ㆍ군 도로업무 담당자... ",
      "pubDate": "Tue, 10 Jul 2018 11:20:00 +0900"
    },
    {
      "title": "제10대 <b>경기도</b>의회 개원",
      "originallink": "http://news1.kr/photos/view/?3200027",
      "link": "http://news.naver.com/main/read.nhn?mode=LSD&mid=sec&sid1=102&oid=421&aid=0003474365",
      "description": "이재명 <b>경기도</b>지사, <b>경기도</b> 간부공무원들과 의원들이 10일 오후 <b>경기도</b> 수원시 <b>경기도</b>의회 본회의장에서 열린 제10대 <b>경기도</b>의회 개원식에 참석해 자리에 앉아 있다. 2018.7.10/뉴스1 5zzang@news1.kr ▶ [뉴스1]... ",
      "pubDate": "Tue, 10 Jul 2018 15:07:00 +0900"
    },
    {
      "title": "제10대 <b>경기도</b>의회 개원식, 축사하는 이재명 도지사",
      "originallink": "http://news1.kr/photos/view/?3200042",
      "link": "http://news.naver.com/main/read.nhn?mode=LSD&mid=sec&sid1=102&oid=421&aid=0003474386",
      "description": "이재명 <b>경기도</b>지사가 10일 오후 <b>경기도</b> 수원시 <b>경기도</b>의회 본회의장에서 열린 제10대 <b>경기도</b>의회 개원식에 참석해 축사를 하고 있다. 2018.7.10/뉴스1 5zzang@news1.kr ▶ [뉴스1] 채널설정하기 ▶ 제보하기... ",
      "pubDate": "Tue, 10 Jul 2018 15:09:00 +0900"
    },
    {
      "title": "선서하는 제10대 <b>경기도</b>의회 의원들",
      "originallink": "http://news1.kr/photos/view/?3200184",
      "link": "http://news.naver.com/main/read.nhn?mode=LSD&mid=sec&sid1=102&oid=421&aid=0003474535",
      "description": "10일 오후 <b>경기도</b> 수원시 <b>경기도</b>의회 본회의장에서 열린 제10대 <b>경기도</b>의회 개원식에 참석한 의원들이 선서를 하고 있다. 2018.7.10/뉴스1 5zzang@news1.kr ▶ [뉴스1] 채널설정하기 ▶ 제보하기 ▶ 2018 러시아... ",
      "pubDate": "Tue, 10 Jul 2018 15:39:00 +0900"
    },
    {
      "title": "<b>경기도</b> 버스 준공영제 폐지…경기교통공사 설립",
      "originallink": "http://www.obsnews.co.kr/news/articleView.html?idxno=1104690",
      "link": "http://www.obsnews.co.kr/news/articleView.html?idxno=1104690",
      "description": "이재명 <b>경기도</b>지사 인수위원회가 남경필표 버스준공영제를 폐지하고, 공항버스도 한정면허로 되돌리기로 했습니다. <b>경기도</b> 교통을 책임질 공사도 만들기로 했습니다. 강병호 기자입니다. 【기자】 이재명 <b>경기도</b>지사... ",
      "pubDate": "Tue, 10 Jul 2018 21:10:00 +0900"
    },
    {
      "title": "이재명 <b>경기도</b>지사, <b>경기도</b>의회 개원식 축사",
      "originallink": "http://news1.kr/photos/view/?3200040",
      "link": "http://news.naver.com/main/read.nhn?mode=LSD&mid=sec&sid1=102&oid=421&aid=0003474387",
      "description": "이재명 <b>경기도</b>지사가 10일 오후 <b>경기도</b> 수원시 <b>경기도</b>의회 본회의장에서 열린 제10대 <b>경기도</b>의회 개원식에 참석해 축사를 하고 있다. 2018.7.10/뉴스1 5zzang@news1.kr ▶ [뉴스1] 채널설정하기 ▶ 제보하기... ",
      "pubDate": "Tue, 10 Jul 2018 15:09:00 +0900"
    },
    {
      "title": "제10대 <b>경기도</b>의회, 송한준 의장 선출",
      "originallink": "http://www.joongboo.com/?mod=news&act=articleView&idxno=1266757",
      "link": "http://www.joongboo.com/?mod=news&act=articleView&idxno=1266757",
      "description": "▲ 10일 선출된 <b>경기도</b>의회 송한준 의장이 제329회 도의회 임시회를 본회의장에서 진행하고 있다. 사진=<b>경기도</b>의회 제10대 <b>경기도</b>의회가 전반기 의장에 송한준 의장을 선출하는 등 첫 임시회를 개회하며 공식... ",
      "pubDate": "Tue, 10 Jul 2018 22:52:00 +0900"
    },
    {
      "title": "<b>경기도</b> 통상촉진단, UAE 724만 달러 수출 '낭보'",
      "originallink": "http://www.asiatime.co.kr/news/articleView.html?idxno=187539",
      "link": "http://www.asiatime.co.kr/news/articleView.html?idxno=187539",
      "description": "[아시아타임즈=권혁철 기자] <b>경기도</b>내 수출 유망 중소기업 10개사가 아랍에미리트(UAE) 시장 판로 개척의... <b>경기도</b>는 (재)<b>경기도</b>경제과학진흥원와 함께 '2018 <b>경기도</b> UAE 통상촉진단'을 구성해 지난달 25일부터 30일까지... ",
      "pubDate": "Tue, 10 Jul 2018 10:39:00 +0900"
    },
    {
      "title": "제10대 <b>경기도</b>의회, 송한준 의장 김원기·안혜영 부의장",
      "originallink": "http://www.newscj.com/news/articleView.html?idxno=536398",
      "link": "http://www.newscj.com/news/articleView.html?idxno=536398",
      "description": "10일 <b>경기도</b>의회 대회의실에서 제10대 의회를 이끌어갈 의장으로 당선된 송한준 의원이 인사를 하고 있다. (제공: <b>경기도</b>의회) ⓒ천지일보(뉴스천지) 2018.7.10 제329회 임시회 원구성   <b>경기도</b>의회가 10일 대회의실에서... ",
      "pubDate": "Tue, 10 Jul 2018 12:40:00 +0900"
    },
    {
      "title": "국민의례하는 <b>경기도</b>의회 의원들",
      "originallink": "http://news1.kr/photos/view/?3200176",
      "link": "http://news.naver.com/main/read.nhn?mode=LSD&mid=sec&sid1=102&oid=421&aid=0003474524",
      "description": "10일 오후 <b>경기도</b> 수원시 <b>경기도</b>의회 본회의장에서 열린 제10대 <b>경기도</b>의회 개원식에 참석한 의원들이 국민의례를 하고 있다. 2018.7.10/뉴스1 5zzang@news1.kr ▶ [뉴스1] 채널설정하기 ▶ 제보하기 ▶ 2018... ",
      "pubDate": "Tue, 10 Jul 2018 15:37:00 +0900"
    },
    {
      "title": "이화영 <b>경기도</b> 연정부지사, 10일 공식 취임",
      "originallink": "http://news.hankyung.com/article/201807106629h",
      "link": "http://news.naver.com/main/read.nhn?mode=LSD&mid=sec&sid1=102&oid=015&aid=0003976765",
      "description": "10일 이화영(사진 오른쪽) <b>경기도</b> 연정부지사가 이재명 도지사로부터 임명장을 받고 공식 취임했다. <b>경기도</b> 제공 <b>경기도</b>는 이화영 연정부지사가 공식 취임했다고 10일 발표했다. 이 부지사는 서면 취임사를 통해... ",
      "pubDate": "Tue, 10 Jul 2018 15:37:00 +0900"
    },
    {
      "title": "국무총리기 검도대회 <b>경기도</b> '종합 우승'",
      "originallink": "http://www.gnmaeil.com/news/articleView.html?idxno=376640",
      "link": "http://www.gnmaeil.com/news/articleView.html?idxno=376640",
      "description": "이날 대회 결과, <b>경기도</b>가 종합우승의 영예를 안았으며 2위는 인천광역시, 3위는 강원도가 각각 차지했다. 또 단체전에서는 초등학생ㆍ청소년ㆍ여자ㆍ남자중년부에서 <b>경기도</b>가 우승을 차지했으며 대학동아리부에... ",
      "pubDate": "Tue, 10 Jul 2018 00:13:00 +0900"
    },
    {
      "title": "<b>경기도</b>, 일반인 대상 책 출간 프로젝트 공모",
      "originallink": "http://news.mt.co.kr/mtview.php?no=2018071110083057087",
      "link": "http://news.naver.com/main/read.nhn?mode=LSD&mid=sec&sid1=102&oid=008&aid=0004076773",
      "description": "[8월 1일부터 15일까지 수필, 그림책, 단편소설 분야 원고 공모] <b>경기도</b>가 일반인 책 출간 프로젝트 '경기... 출판 경험이 없는 <b>경기도</b>민이라면 누구나 응모할 수 있다. 수필과 단편소설 분야는 A4용지 30쪽(글자 크기... ",
      "pubDate": "Wed, 11 Jul 2018 10:42:00 +0900"
    },
    {
      "title": "<b>경기도</b>인수위, 대중교통생태계 전환 플랜 발표",
      "originallink": "http://www.sporbiz.co.kr/news/articleView.html?idxno=253224",
      "link": "http://www.sporbiz.co.kr/news/articleView.html?idxno=253224",
      "description": "[한국스포츠경제 김원태] 민선7기 <b>경기도</b>지사직 인수위원회 ‘교통대책특별위원회’가 10일 정례브리핑을... 민선7기 <b>경기도</b> 교통정책의 핵심의제로 선정해 이재명 <b>경기도</b>지사의 교통공약 이행방안을 제시했다. 먼저... ",
      "pubDate": "Tue, 10 Jul 2018 17:37:00 +0900"
    },
    {
      "title": "제10대 <b>경기도</b>의회 10일 개원",
      "originallink": "http://www.cnbnews.com/news/article.html?no=379202",
      "link": "http://www.cnbnews.com/news/article.html?no=379202",
      "description": "▲ CNB뉴스, CNBNEWS, 씨앤비뉴스 6.13 지방선거를 통해 142명으로 구성된 제10대 <b>경기도</b>의회가 10일, 개원식을... 제10대 <b>경기도</b>의회 전반기를 이끌게 됐다. 부의장에는 3선의 더불어민주당 김원기 의원과 안혜영 의원이... ",
      "pubDate": "Tue, 10 Jul 2018 17:12:00 +0900"
    },
    {
      "title": "<b>경기도</b>, 제1회 도로안전 포럼 개최",
      "originallink": "http://www.newscj.com/news/articleView.html?idxno=536411",
      "link": "http://www.newscj.com/news/articleView.html?idxno=536411",
      "description": "기법토의  <b>경기도</b>가 오는 11일 오후 2시부터 '세종~구리 고속도로 사업' 현장서 도 및 시·군 도로업무 담당자 100여명이 참여한 가운데 올해 첫 '<b>경기도</b> 도로안전 포럼'을 개최한다고 밝혔다. '<b>경기도</b> 도로안전 포럼'은... ",
      "pubDate": "Tue, 10 Jul 2018 13:00:00 +0900"
    },
    {
      "title": "제10대 <b>경기도</b>의회 개원…송한준 의장 선출",
      "originallink": "http://news.kbs.co.kr/news/view.do?ncd=4006932&ref=A",
      "link": "http://news.naver.com/main/read.nhn?mode=LSD&mid=sec&sid1=102&oid=056&aid=0010596418",
      "description": "제10대 <b>경기도</b>의회가 오늘(10일) 첫 임시회를 열고, 23일까지 14일간의 일정에 들어갔습니다. 10대 <b>경기도</b>의회의 재적 의원은 142명이며 정당별 의원 수는 더불어민주당 135명, 자유한국당 4명, 정의당 2명, 바른미래당... ",
      "pubDate": "Tue, 10 Jul 2018 13:23:00 +0900"
    },
    {
      "title": "이화영 <b>경기도</b> 연정부지사, 10일 공식 취임",
      "originallink": "http://www.nspna.com/news/?mode=view&newsid=293242",
      "link": "http://www.nspna.com/news/?mode=view&newsid=293242",
      "description": "(경기=NSP통신) 김여울 기자 = 이화영 <b>경기도</b> 연정부지사가 10일 오전 이재명 <b>경기도</b>지사로부터 임명장을 받고 공식 취임했다. 이화영 부지사는 이날 서면으로 발표한 취임사를 통해 “지금의 대한민국은 4.27... ",
      "pubDate": "Tue, 10 Jul 2018 17:30:00 +0900"
    },
    {
      "title": "제10대 <b>경기도</b>의회 개원식",
      "originallink": "http://news1.kr/photos/view/?3200193",
      "link": "http://news.naver.com/main/read.nhn?mode=LSD&mid=sec&sid1=102&oid=421&aid=0003474548",
      "description": "10일 오후 <b>경기도</b> 수원시 <b>경기도</b>의회 본회의장에서 열린 제10대 <b>경기도</b>의회 개원식에 참석한 의원들이 선서를 하고 있다. 2018.7.10/뉴스1 5zzang@news1.kr ▶ [뉴스1] 채널설정하기 ▶ 제보하기 ▶ 2018 러시아... ",
      "pubDate": "Tue, 10 Jul 2018 15:44:00 +0900"
    },
    {
      "title": "선서하는 <b>경기도</b>의회 의원들",
      "originallink": "http://news1.kr/photos/view/?3200047",
      "link": "http://news.naver.com/main/read.nhn?mode=LSD&mid=sec&sid1=102&oid=421&aid=0003474391",
      "description": "10일 오후 <b>경기도</b> 수원시 <b>경기도</b>의회 본회의장에서 열린 제10대 <b>경기도</b>의회 개원식에 참석한 의원들이 선서를 하고 있다. 2018.7.10/뉴스1 5zzang@news1.kr ▶ [뉴스1] 채널설정하기 ▶ 제보하기 ▶ 2018 러시아... ",
      "pubDate": "Tue, 10 Jul 2018 15:10:00 +0900"
    },
    {
      "title": "이화영 <b>경기도</b> 연정부지사 10일 공식 취임",
      "originallink": "http://www.suwon.com/news/articleView.html?idxno=125720",
      "link": "http://www.suwon.com/news/articleView.html?idxno=125720",
      "description": "&lt;사진= <b>경기도</b>&gt; 이재명 <b>경기도</b>지사(왼쪽)가 이화영 연정부지사에게 임명장을 수여하고 기념사진을 찍고 있다. &lt;사진= <b>경기도</b>&gt; 이화영 <b>경기도</b> 연정부지사가 10일 오전 이재명 <b>경기도</b>지사로부터 임명장을 받고 공식 취임했다.... ",
      "pubDate": "Tue, 10 Jul 2018 17:10:00 +0900"
    },
    {
      "title": "<b>경기도</b>, 축령산 자연휴양림 ‘야외 물놀이장’ 개장",
      "originallink": "http://www.ekn.kr/news/article.html?no=373486",
      "link": "http://www.ekn.kr/news/article.html?no=373486",
      "description": "[수원=에너지경제신문 좌승훈 기자] <b>경기도</b> 산림환경연구소는 본격적인 여름 휴가철인 오는 13일부터 다음달 24일까지 남양주 수동면 축령산자연휴양림 내 ‘야외 물놀이장’을 개장·운영한다. 축령산자연휴양림은... ",
      "pubDate": "Wed, 11 Jul 2018 13:26:00 +0900"
    },
    {
      "title": "[포토] <b>경기도</b> 지방세 체납자 압류 동산 공매",
      "originallink": "http://view.asiae.co.kr/news/view.htm?idxno=2018071111174508376",
      "link": "http://news.naver.com/main/read.nhn?mode=LSD&mid=sec&sid1=102&oid=277&aid=0004274997",
      "description": "11일 <b>경기도</b> 고양시 킨텍스에서 열린 '지방세 체납자 압류 동산 공매'에서 참가자들이 압류품을 살펴보고 있다. / ▶ 양낙규의 '군사이야기' ▶ 재미와 신기 '과학을읽다' &lt;ⓒ세계를 보는 창 경제를 보는 눈, 아시아경제... ",
      "pubDate": "Wed, 11 Jul 2018 11:17:00 +0900"
    },
    {
      "title": "<b>경기도</b> '도로안전 포럼' 개최",
      "originallink": "http://view.asiae.co.kr/news/view.htm?idxno=2018071007302076672",
      "link": "http://news.naver.com/main/read.nhn?mode=LSD&mid=sec&sid1=102&oid=277&aid=0004273974",
      "description": "[아시아경제(수원)=이영규 기자] <b>경기도</b>가 '도로안전 포럼'을 개최한다. <b>경기도</b>는 11일 '세종~구리 고속도로 사업' 현장서 도 및 시ㆍ군 도로업무 담당자 100여명이 참석한 가운데 올해 첫 '<b>경기도</b> 도로안전 포럼'을... ",
      "pubDate": "Tue, 10 Jul 2018 07:30:00 +0900"
    },
    {
      "title": "<b>경기도</b>교육청, 학교폭력 관련 법률 지원 연수",
      "originallink": "http://www.kgdm.co.kr/news/articleView.html?idxno=509358",
      "link": "http://www.kgdm.co.kr/news/articleView.html?idxno=509358",
      "description": "[<b>경기도</b>민일보 우영식기자] <b>경기도</b>교육청은 12일부터 17일까지 3차에 걸쳐 북부청사 및 <b>경기도</b>교육복지센터에서 '2018년 학교폭력 관련 법률 지원 연수'를 실시한다고 11잉 밝혔다. 이번 연수는 학교폭력 사안에 대한... ",
      "pubDate": "Wed, 11 Jul 2018 19:50:00 +0900"
    },
    {
      "title": "제10대 <b>경기도</b>의회 개원식",
      "originallink": "http://news1.kr/photos/view/?3200180",
      "link": "http://news.naver.com/main/read.nhn?mode=LSD&mid=sec&sid1=102&oid=421&aid=0003474532",
      "description": "10일 오후 <b>경기도</b> 수원시 <b>경기도</b>의회 본회의장에서 열린 제10대 <b>경기도</b>의회 개원식에 참석한 의원들이 자리에 앉아 있다. 2018.7.10/뉴스1 5zzang@news1.kr ▶ [뉴스1] 채널설정하기 ▶ 제보하기 ▶ 2018 러시아... ",
      "pubDate": "Tue, 10 Jul 2018 15:38:00 +0900"
    },
    {
      "title": "<b>경기도</b> 통상촉진단, UAE서 724만 달러 계약추진",
      "originallink": "http://www.joongboo.com/?mod=news&act=articleView&idxno=1266574",
      "link": "http://www.joongboo.com/?mod=news&act=articleView&idxno=1266574",
      "description": "<b>경기도</b>의 지원을 받은 수출 유망 중소기업 10개사가 아랍에미리트(UAE) 시장에서 724만 달러 상당의 계약추진 실적을 거뒀다. 10일 <b>경기도</b>에 따르면 중동시장 개척을 위해 <b>경기도</b> 주최, (재)<b>경기도</b>경제과학진흥원... ",
      "pubDate": "Tue, 10 Jul 2018 22:34:00 +0900"
    },
    {
      "title": "이화영 <b>경기도</b> 연정부지사 취임···공식업무 수행",
      "originallink": "http://www.sedaily.com/NewsView/1S214HX0V1",
      "link": "http://news.naver.com/main/read.nhn?mode=LSD&mid=sec&sid1=102&oid=011&aid=0003344678",
      "description": "이화영(오른쪽) <b>경기도</b> 연정부지사가 10일 이재명(왼쪽) <b>경기도</b>지사로부터 임명장을 받고 기념촬영을하고 있다. /사진제공=<b>경기도</b>청 [서울경제] 이화영 <b>경기도</b> 연정부지사가 10일 이재명 <b>경기도</b>지사로부터 임명장을... ",
      "pubDate": "Tue, 10 Jul 2018 13:15:00 +0900"
    },
    {
      "title": "<b>경기도</b>, ‘2017년 성별영향평가 추진 우수기관’으로 선정",
      "originallink": "http://www.viva100.com/main/view.php?key=20180709010003302",
      "link": "http://www.viva100.com/main/view.php?key=20180709010003302",
      "description": "<b>경기도</b>, ‘2017년 성별영향평가 추진 우수기관’으로 선정 <b>경기도</b>가 여성가족부의 ‘2017년 성별영향평가 추진 우수기관’으로 선정돼 지난 5일 양성평등주간 기념식에서 국무총리 표창을 수상했다. 여성가족부는... ",
      "pubDate": "Tue, 10 Jul 2018 09:45:00 +0900"
    },
    {
      "title": "[사설] 부동산 허위 매물 <b>경기도</b>가 제일 많은데 / 공정거래 문란 범죄인데 왜...",
      "originallink": "http://www.kyeonggi.com/?mod=news&act=articleView&idxno=1495747",
      "link": "http://www.kyeonggi.com/?mod=news&act=articleView&idxno=1495747",
      "description": "부끄럽게도 <b>경기도</b>가 1등이다. 허위 매물로 제재를 받은 중개업소는 1천392곳이다. 이 가운데 <b>경기도</b>가 829건이다. 서울시(801건)보다도 많다. 시군별로 보면 용인지역 중개업소가 192건으로 가장 많다. 다음으로 화성시... ",
      "pubDate": "Tue, 10 Jul 2018 21:10:00 +0900"
    },
    {
      "title": "<b>경기도</b>교육연수원, ‘행정실무사, 소통과 협업의 학교문화 만들기’연수 실시",
      "originallink": "http://www.viva100.com/main/view.php?key=20180709010003323",
      "link": "http://www.viva100.com/main/view.php?key=20180709010003323",
      "description": "<b>경기도</b>교육연수원, ‘행정실무사, 소통과 협업의 학교문화 만들기’연수 실시 <b>경기도</b>교육청 소속 <b>경기도</b>교육연수원(원장 이범희)은 7월 11일부터 13일까지 <b>경기도</b>교육연수원에서 ‘행정실무사, 소통과 협업의 학교문화... ",
      "pubDate": "Tue, 10 Jul 2018 09:43:00 +0900"
    },
    {
      "title": "제27회 <b>경기도</b> 청소년 연극 축제 개최",
      "originallink": "http://www.viva100.com/main/view.php?key=20180709010003304",
      "link": "http://www.viva100.com/main/view.php?key=20180709010003304",
      "description": "제27회 <b>경기도</b> 청소년 연극 축제 개최 제27회 <b>경기도</b>청소년연극제가 3일 경기 동부권역(양평군)을 시작으로 서부권역(김포시), 남부권역(평택시), 북부권역(파주시) 등 4개 권역에서 한 달여 동안 예선대회를... ",
      "pubDate": "Tue, 10 Jul 2018 09:43:00 +0900"
    },
    {
      "title": "제10대 <b>경기도</b>의회 상임위 확정",
      "originallink": "http://kpenews.com/Board.aspx?BoardNo=16037",
      "link": "http://kpenews.com/Board.aspx?BoardNo=16037",
      "description": "(사진=<b>경기도</b>의회) [한국정경신문=이근항 기자] 제10대 <b>경기도</b>의회 전반기 상임위원장과 다수당인 더불어민주당 수석대표단이 9일 구성돼 본격적인 의정활동에 들어갔다. 염종현 더불어민주당 대표의원은 “의원들의... ",
      "pubDate": "Tue, 10 Jul 2018 11:01:00 +0900"
    },
    {
      "title": "<b>경기도</b>, '작은 도서관' 42곳 선정…독서 활성화",
      "originallink": "http://www.newsis.com/view/?id=NISX20180711_0000360410&cID=10803&pID=14000",
      "link": "http://news.naver.com/main/read.nhn?mode=LSD&mid=sec&sid1=102&oid=003&aid=0008698873",
      "description": "【수원=뉴시스】 수도권취재팀 = <b>경기도</b>는 작은도서관 활성화를 위한 ‘2018 하반기 작은도서관 독서문화프로그램 운영 지원’ 대상 도서관 42곳을 선정했다고 11일 밝혔다. 선정된 작은도서관은 개소당 최대 170만원까지... ",
      "pubDate": "Wed, 11 Jul 2018 09:27:00 +0900"
    },
    {
      "title": "대구·<b>경기도</b> 시흥시, 데이터기반 스마트시티 실증도시 선정",
      "originallink": "http://www.electimes.com/article.php?aid=1531189069160971013",
      "link": "http://www.electimes.com/article.php?aid=1531189069160971013",
      "description": "<b>경기도</b> 시흥시가 데이터기반 스마트시티 실증도시로 선정됐다. 국토교통부(장관 김현미)와 과학기술정보통신부(장관 유영민)는 데이터 기반 스마트시티’ 연구개발 사업의 실증도시로 대구광역시와 <b>경기도</b> 시흥시 등... ",
      "pubDate": "Tue, 10 Jul 2018 11:18:00 +0900"
    },
    {
      "title": "이화영 <b>경기도</b> 연정부지사, 7월 10일 오전 '공식 취임'",
      "originallink": "http://www.ilyoseoul.co.kr/news/articleView.html?idxno=241945",
      "link": "http://www.ilyoseoul.co.kr/news/articleView.html?idxno=241945",
      "description": "[일요서울｜수원 강의석 기자]  이화영 <b>경기도</b> 연정부지사가 10일 오전 이재명 <b>경기도</b>지사로부터 임명장을 받고 공식 취임했다. 이화영 부지사는 이날 서면으로 발표한 취임사를 통해 &quot;지금의... ",
      "pubDate": "Tue, 10 Jul 2018 13:14:00 +0900"
    },
    {
      "title": "공항버스 원상복구·준공영제 중지...<b>경기도</b> 버스정책 뒤집힌다",
      "originallink": "http://www.joongboo.com/?mod=news&act=articleView&idxno=1266755",
      "link": "http://www.joongboo.com/?mod=news&act=articleView&idxno=1266755",
      "description": "▲ <b>경기도</b> 버스. 사진=연합 <b>경기도</b> 버스정책이 짧게는 한 달, 길게는 석달 만에 뒤엎어졌다. 민선 7기 <b>경기도</b>지사직 인수위원회가 공항버스의 시외면허 취소 및 한정면허 복원과 현재 시행 중인 광역버스 준공영제 중지... ",
      "pubDate": "Tue, 10 Jul 2018 22:55:00 +0900"
    },
    {
      "title": "<b>경기도</b>, 아파트 거주 위기가구 2,612세대 긴급지원",
      "originallink": "http://www.breaknews.com/sub_read.html?uid=588858&section=sc2",
      "link": "http://www.breaknews.com/sub_read.html?uid=588858&section=sc2",
      "description": "▲ <b>경기도</b>청전경 (C)운영자 <b>경기도</b>가 아파트에 거주하는 복지사각지대 위기가구 2,612세대를 발굴해 긴급 지원했다. 도는 충북 증평군 모녀 사망 사건을 계기로 아파트 거주 위기가구에 대한 조사를 4월 중순부터... ",
      "pubDate": "Tue, 10 Jul 2018 07:54:00 +0900"
    },
    {
      "title": "승부차기의 역설···한 <b>경기도</b> 못이기고 월드컵 우승 가능하다고?",
      "originallink": "http://premium.mk.co.kr/view.php?no=22838",
      "link": "http://sports.news.naver.com/wfootball/news/read.nhn?oid=009&aid=0004181881",
      "description": "승부차기 하기 전까지 해당 경기의 최종 스코어는 1대1이 15경기로 가장 많았고, 0대0 <b>경기도</b> 11경기나 되었다.... 게다가 월드컵 같은 세계 최고의 스포츠대회에서 공식적으로 한 <b>경기도</b> 이기지 않아도 이론상 우승이... ",
      "pubDate": "Tue, 10 Jul 2018 06:02:00 +0900"
    },
    {
      "title": "<b>경기도</b> '버스 준공영제' 중지...노선입찰제 중심 '새경기 준공영제' 도입",
      "originallink": "http://www.newsworks.co.kr/news/articleView.html?idxno=199424",
      "link": "http://www.newsworks.co.kr/news/articleView.html?idxno=199424",
      "description": "&lt;사진=<b>경기도</b>&gt; [뉴스웍스=한민재 기자] 새로운경기위원회는 현재 시행중인 준공영제를 중지하고... <b>경기도</b> 시내버스 준공영제 운영에 관한 조례제20조(준공영제 중지)에 따라, 준공영제 중지는 충분히 가능하다는 게 특위의... ",
      "pubDate": "Tue, 10 Jul 2018 11:53:00 +0900"
    },
    {
      "title": "<b>경기도</b> 정보소외계층 300여 명 첨단 로봇 등 IT세상 체험",
      "originallink": "http://www.m-i.kr/news/articleView.html?idxno=432086",
      "link": "http://www.m-i.kr/news/articleView.html?idxno=432086",
      "description": "[매일일보 강세근 기자]  <b>경기도</b>는 정보소외계층 정보화교육대상자 300여 명을 대상으로 춘천... <b>경기도</b>는 정보소외계층의 정보화 마인드 향상과 건강한 정보문화 조성을 위해 2014부터 해마다 IT... ",
      "pubDate": "Tue, 10 Jul 2018 10:23:00 +0900"
    },
    {
      "title": "<b>경기도</b>, 아파트 거주 위기가구 2천612가구 발굴 긴급 지원",
      "originallink": "http://www.ikld.kr/news/articleView.html?idxno=96459",
      "link": "http://www.ikld.kr/news/articleView.html?idxno=96459",
      "description": "<b>경기도</b>청 전경. [국토일보 김주영 기자] <b>경기도</b>가 복지 사각지대에 있는 위기 가구를 선제 발굴해 어려움을 해소하기 위한 '찾아가는 행정 서비스'를 구현했다.  앞으로도 지속적인 모니터링을 통해... ",
      "pubDate": "Tue, 10 Jul 2018 09:26:00 +0900"
    },
    {
      "title": "이화영 <b>경기도</b> ‘평화부지사’ 취임…“통일경제특구 추진”",
      "originallink": "http://www.seoul.co.kr/news/newsView.php?id=20180710500073&wlog_tag3=naver",
      "link": "http://news.naver.com/main/read.nhn?mode=LSD&mid=sec&sid1=004&oid=081&aid=0002928423",
      "description": "[서울신문] 이화영 <b>경기도</b> 평화부지사가 10일 이재명 지사로부터 임명장을 받고 공식 취임했다. 이재명... 이 부지사는 취임식을 생략한 채 <b>경기도</b>청 북부청사 상황실로 이동해 경기북부 균형발전과 평화 관련 공약 등을... ",
      "pubDate": "Tue, 10 Jul 2018 14:36:00 +0900"
    },
    {
      "title": "제10대 <b>경기도</b>의회 개원식",
      "originallink": "http://news1.kr/photos/view/?3200052",
      "link": "http://news.naver.com/main/read.nhn?mode=LSD&mid=sec&sid1=102&oid=421&aid=0003474398",
      "description": "이재명 <b>경기도</b>지사가 10일 오후 <b>경기도</b> 수원시 <b>경기도</b>의회 본회의장에서 열린 제10대 <b>경기도</b>의회 개원식에 참석해 축사를 하고 있다. 2018.7.10/뉴스1 5zzang@news1.kr ▶ [뉴스1] 채널설정하기 ▶ 제보하기... ",
      "pubDate": "Tue, 10 Jul 2018 15:10:00 +0900"
    },
    {
      "title": "제10대 <b>경기도</b>의회 개원",
      "originallink": "http://www.asiatoday.co.kr/view.php?key=20180710010005962",
      "link": "http://www.asiatoday.co.kr/view.php?key=20180710010005962",
      "description": "전반기 의장 송한준, 부의장 김원기, 안혜영 선출 제10대 <b>경기도</b>의회의원들이 의회 청사 앞에서 파이팅을 외치며 개원 기념촬영을 했다. /제공 = <b>경기도</b>의회수원/아시아투데이 김주홍 기자 = <b>경기도</b>의회가 10일... ",
      "pubDate": "Tue, 10 Jul 2018 15:08:00 +0900"
    }
  ]
}